cov/.plugin.py.swp
cov/plugin.py
pytest_cocotb_cov-0.1.0.dist-info/METADATA
pytest_cocotb_cov-0.1.0.dist-info/WHEEL
pytest_cocotb_cov-0.1.0.dist-info/RECORD
